py_pifuhd/__init__.py
py_pifuhd/opt.py
py_pifuhd/test.py
py_pifuhd/apps/__init__.py
py_pifuhd/apps/crop_img.py
py_pifuhd/apps/eval.py
py_pifuhd/apps/prt_util.py
py_pifuhd/apps/render_data.py
py_pifuhd/apps/render_multi_people.py
py_pifuhd/apps/train_color.py
py_pifuhd/apps/train_shape.py
py_pifuhd/checkpoints/__init__.py
py_pifuhd/configs/PIFuhd_Render_People_HG_coarse.py
py_pifuhd/configs/PIFuhd_Render_People_HG_fine.py
py_pifuhd/configs/PIFuhd_Render_People_HG_normal_map.py
py_pifuhd/configs/__init__.py
py_pifuhd/data/__init__.py
py_pifuhd/engineer/__init__.py
py_pifuhd/engineer/core/__init__.py
py_pifuhd/engineer/core/eval.py
py_pifuhd/engineer/core/train.py
py_pifuhd/engineer/datasets/CartonDataset.py
py_pifuhd/engineer/datasets/RPDataset.py
py_pifuhd/engineer/datasets/__init__.py
py_pifuhd/engineer/datasets/builder.py
py_pifuhd/engineer/datasets/registry.py
py_pifuhd/engineer/datasets/loader/__init__.py
py_pifuhd/engineer/datasets/loader/build_loader.py
py_pifuhd/engineer/datasets/pipelines/__init__.py
py_pifuhd/engineer/datasets/pipelines/compose.py
py_pifuhd/engineer/datasets/pipelines/formating.py
py_pifuhd/engineer/datasets/pipelines/process.py
py_pifuhd/engineer/models/__init__.py
py_pifuhd/engineer/models/builder.py
py_pifuhd/engineer/models/registry.py
py_pifuhd/engineer/models/PIFu/BasePIFu.py
py_pifuhd/engineer/models/PIFu/PIFu.py
py_pifuhd/engineer/models/PIFu/PIFuhd.py
py_pifuhd/engineer/models/PIFu/__init__.py
py_pifuhd/engineer/models/backbones/Hourglass.py
py_pifuhd/engineer/models/backbones/__init__.py
py_pifuhd/engineer/models/backbones/base_backbone.py
py_pifuhd/engineer/models/common/__init__.py
py_pifuhd/engineer/models/common/net_utils.py
py_pifuhd/engineer/models/depthnormalizer/DepthNormalizer.py
py_pifuhd/engineer/models/depthnormalizer/__init__.py
py_pifuhd/engineer/models/heads/PIFuhd_Surface_head.py
py_pifuhd/engineer/models/heads/Surface_Head.py
py_pifuhd/engineer/models/heads/__init__.py
py_pifuhd/engineer/models/heads/base_head.py
pypifuhd-2.0.0.dist-info/LICENSE
pypifuhd-2.0.0.dist-info/METADATA
pypifuhd-2.0.0.dist-info/WHEEL
pypifuhd-2.0.0.dist-info/entry_points.txt
pypifuhd-2.0.0.dist-info/top_level.txt
pypifuhd-2.0.0.dist-info/RECORD
