Metadata-Version: 2.1
Name: pypifuhd
Version: 2.0.0
Summary: pypifuhd: Python tools for processing 3D face
Home-page: https://github.com/lingtengqiu/Open-PIFuhd
Author: lingtengqiu
License: MIT
Platform: UNKNOWN
Classifier: License :: OSI Approved :: MIT License
Classifier: Programming Language :: Python :: 3
Classifier: Programming Language :: Python :: 3.9
License-File: LICENSE
Requires-Dist: torch (==1.9.0)
Requires-Dist: torchvision (==0.10.0)
Requires-Dist: mmcv (==1.3.10)
Requires-Dist: trimesh (==3.9.25)
Requires-Dist: scipy (==1.7.0)
Requires-Dist: einops (==0.3.0)
Requires-Dist: Pillow (==8.3.1)
Requires-Dist: scikit-image (==0.18.2)
Requires-Dist: tqdm (==4.61.2)
Requires-Dist: opencv-python (==4.5.3.56)
Requires-Dist: PyOpenGL (==3.1.5)
Requires-Dist: cython (==0.29.24)
Requires-Dist: rtree (==0.9.7)
